mac_format/__init__.py
mac_format/__main__.py
mac_format/mac_formater.py
mac_format-0.2.1.dist-info/WHEEL
mac_format-0.2.1.dist-info/METADATA
mac_format-0.2.1.dist-info/RECORD
