Metadata-Version: 2.1
Name: mac-format
Version: 0.2.1
Summary: 
Home-page: https://github.com/lbmello/mac_format/
Author: Lucas
Author-email: lucasbmello96@gmail.com
Requires-Python: >=3.9,<4.0
Classifier: Programming Language :: Python :: 3
Classifier: Programming Language :: Python :: 3.9
Requires-Dist: requests (>=2.27.0,<3.0.0)
Project-URL: Repository, https://github.com/lbmello/mac_format/
